echelle_spectra/__init__.py
echelle_spectra/__main__.py
echelle_spectra/echelle_spectra_gui.py
echelle_spectra/examples/1.1_Cutting_Pattern_Synthetic.ipynb
echelle_spectra/examples/1.1_Cutting_Pattern_Synthetic.pdf
echelle_spectra/examples/1.2_Cutting_Pattern_Masks.ipynb
echelle_spectra/examples/1.2_Cutting_Pattern_Masks.pdf
echelle_spectra/examples/CCD_cut.png
echelle_spectra/examples/CMOS_cut.png
echelle_spectra/examples/pattern.txt
echelle_spectra/examples/pattern_image_synthetic.txt
echelle_spectra/examples/testtool-CCD.ipynb
echelle_spectra/examples/testtool-CCD.pdf
echelle_spectra/examples/testtool-CMOS.ipynb
echelle_spectra/examples/testtool-CMOS.pdf
echelle_spectra/resources/defaults.toml
echelle_spectra/resources/header_template.txt
echelle_spectra/resources/window_layout.py
echelle_spectra/resources/calibration_files/ThAr_10.0s_16bit.sif
echelle_spectra/resources/calibration_files/Th_wavelength.txt
echelle_spectra/resources/calibration_files/Th_wavelength_CMOS.txt
echelle_spectra/resources/calibration_files/Th_wavelength_CMOS_only_Th-Ar.txt
echelle_spectra/resources/calibration_files/absolute_20170613_b8.sif
echelle_spectra/resources/calibration_files/absolute_20170613_b8_0.2_bkg.sif
echelle_spectra/resources/calibration_files/absolute_20170613_b8_0.2_v2.sif
echelle_spectra/resources/calibration_files/integrating_sphere.txt
echelle_spectra/resources/calibration_files/pattern.txt
echelle_spectra/resources/calibration_files/pattern_cmos.txt
echelle_spectra/resources/calibration_files/sphere_CMOS.sif
echelle_spectra/resources/calibration_files/sphere_CMOS_bkg.sif
echelle_spectra/resources/graphics/echelle.png
echelle_spectra/resources/graphics/echelle.svg
echelle_spectra/resources/test_data/CCD_Example.SIF
echelle_spectra/tools/config_loader.py
echelle_spectra/tools/echelle.py
echelle_spectra/tools/emissionbands.py
echelle_spectra/tools/emissiondata.py
echelle_spectra-0.0.2.dist-info/LICENSE
echelle_spectra-0.0.2.dist-info/METADATA
echelle_spectra-0.0.2.dist-info/WHEEL
echelle_spectra-0.0.2.dist-info/entry_points.txt
echelle_spectra-0.0.2.dist-info/top_level.txt
echelle_spectra-0.0.2.dist-info/RECORD
