Metadata-Version: 2.1
Name: echelle-spectra
Version: 0.0.2
Summary: Graphical tool for the extraction and analysis of calibrated spectra from 2D Echelle spectrometer images
Author-email: Kuzmin Arseniy Aleksandrovich <arseniy.a.kuzmin@gmail.com>, Alexander Liptak <alexadner.liptak.jr@googlemail.com>
License: MIT License        
Project-URL: Homepage, https://github.com/queezz/echelle_spectra
Project-URL: Bug Tracker, https://github.com/queezz/echelle_spectra/issues
Keywords: Echelle,echelle,spectra,spectrum,spectrometer,image,calibration,calibrated,analysis,fitting,GUI,UI
Classifier: Development Status :: 4 - Beta
Classifier: Environment :: Console
Classifier: Environment :: X11 Applications :: Qt
Classifier: Intended Audience :: Science/Research
Classifier: License :: OSI Approved :: MIT License
Classifier: Operating System :: OS Independent
Classifier: Programming Language :: Python :: 3
Classifier: Topic :: Scientific/Engineering :: Physics
Requires-Python: >=3.8
License-File: LICENSE
Requires-Dist: lmfit (>=1.0.3)
Requires-Dist: matplotlib (>=3.5.2)
Requires-Dist: numpy (>=1.23.1)
Requires-Dist: pyqt5 (>=5.15.7)
Requires-Dist: pyqtgraph (>=0.12.4)
Requires-Dist: scipy (>=1.8.1)
Requires-Dist: sif-parser (>=0.3.0)
Requires-Dist: tomli (>=2.0.1)
Provides-Extra: dev
Requires-Dist: black ; extra == 'dev'
Requires-Dist: jupyter ; extra == 'dev'
Requires-Dist: peakutils ; extra == 'dev'
Requires-Dist: PyQt5-stubs ; extra == 'dev'
Requires-Dist: twine ; extra == 'dev'
